python_bump_version-0.1.1.dist-info/licenses/LICENSE
version_manager/__init__.py
version_manager/cli.py
version_manager/core.py
version_manager/file_utils.py
version_manager/git_utils.py
python_bump_version-0.1.1.dist-info/METADATA
python_bump_version-0.1.1.dist-info/WHEEL
python_bump_version-0.1.1.dist-info/entry_points.txt
python_bump_version-0.1.1.dist-info/top_level.txt
python_bump_version-0.1.1.dist-info/RECORD
